dbt_schema_builder/__init__.py
dbt_schema_builder/app.py
dbt_schema_builder/builder.py
dbt_schema_builder/queries.py
dbt_schema_builder/relation.py
dbt_schema_builder/schema.py
dbt_schema_builder/schema_builder.py
dbt_schema_builder/snowflake_keywords.yml
dbt_schema_builder/templates/model_sql_pii.tpl
dbt_schema_builder/templates/model_sql_safe.tpl
dbt_schema_builder-0.5.0.dist-info/LICENSE.txt
dbt_schema_builder-0.5.0.dist-info/METADATA
dbt_schema_builder-0.5.0.dist-info/WHEEL
dbt_schema_builder-0.5.0.dist-info/entry_points.txt
dbt_schema_builder-0.5.0.dist-info/top_level.txt
dbt_schema_builder-0.5.0.dist-info/RECORD
