Metadata-Version: 2.1
Name: dbt-schema-builder
Version: 0.5.0
Summary: Automate management of PII redacted schemas for dbt projects.
Home-page: https://github.com/edx/dbt-schema-builder
Author: edX
Author-email: oscm@edx.org
License: AGPL 3.0
Keywords: Python edx dbt schema builder
Classifier: Development Status :: 3 - Alpha
Classifier: Intended Audience :: Developers
Classifier: License :: OSI Approved :: GNU Affero General Public License v3 or later (AGPLv3+)
Classifier: Natural Language :: English
Classifier: Programming Language :: Python :: 3
Classifier: Programming Language :: Python :: 3.8
Requires-Python: >=3.8
License-File: LICENSE.txt
Requires-Dist: dbt-core ==1.7.10
Requires-Dist: dbt-snowflake ==1.7.2
